[{"Label": "T.BOY/ WAY LOT./ESC./ SPTRANS (diesel)", "Value": 3494}, {"Label": "THUNDER + EXECUTIVO (diesel)(E5)", "Value": 6221}, {"Label": "THUNDER + EXECUTIVO 1p (diesel)", "Value": 3491}, {"Label": "THUNDER + LOT./ESC. (diesel)(E5)", "Value": 6222}, {"Label": "THUNDER + LOT./ESC./ SPTRANS  (diesel", "Value": 3492}, {"Label": "THUNDER + NEOSTAR URBANO (diesel)(E5)", "Value": 6223}, {"Label": "THUNDER BOY/ WAY EXECUTIVO 1p (diesel)", "Value": 3493}, {"Label": "THUNDER PLUS EXECUTIVO (diesel)(E5)", "Value": 6224}, {"Label": "THUNDER PLUS EXECUTIVO 1p (diesel)", "Value": 4699}, {"Label": "THUNDER WAY EXECUTIVO (diesel)(E5)", "Value": 6225}, {"Label": "THUNDER WAY LOT./ESC. (diesel)(E5)", "Value": 6226}, {"Label": "THUNDER+ NEOSTAR URBANO (diesel)", "Value": 6227}]