[{"Modelo": "ADV 150", "Anos": ["32000", "2022", "2021"]}, {"Modelo": "AMERICA CLASSIC 1600", "Anos": ["1997"]}, {"Modelo": "BIZ 110i", "Anos": ["32000", "2021", "2020", "2019", "2018", "2017", "2016"]}, {"Modelo": "BIZ 125 ES/ ES F.INJ./ES MIX F.INJECTION", "Anos": ["2015", "2014", "2013", "2012", "2011", "2010", "2009", "2008", "2007", "2006"]}, {"Modelo": "BIZ 125 EX/ 125 EX FLEX", "Anos": ["2015", "2014", "2013", "2012", "2011"]}, {"Modelo": "BIZ 125 KS/ KS F.INJ./KS MIX F.INJECTION", "Anos": ["2012", "2011", "2010", "2009", "2008", "2007", "2006"]}, {"Modelo": "BIZ 125/125i Flex", "Anos": ["32000", "2021", "2020", "2019", "2018", "2017", "2016"]}, {"Modelo": "BIZ 125+", "Anos": ["2010", "2009", "2008", "2007", "2006"]}, {"Modelo": "C 100 BIZ/ 100 BIZ KS", "Anos": ["2015", "2014", "2013", "2005", "2004", "2003", "2002", "2001", "2000", "1999", "1998"]}, {"Modelo": "C 100 BIZ+", "Anos": ["2005", "2004", "2003", "2002"]}, {"Modelo": "C 100 BIZ-ES", "Anos": ["2015", "2014", "2013", "2012", "2006", "2005", "2004", "2003", "2002", "2001", "2000", "1999"]}, {"Modelo": "C 100 DREAM", "Anos": ["1998", "1997", "1996", "1995", "1994", "1993"]}, {"Modelo": "CB 1000R/ABS", "Anos": ["32000", "2021", "2020", "2019", "2016", "2015", "2014", "2013", "2012", "2011"]}, {"Modelo": "CB 300R/ 300R FLEX", "Anos": ["2015", "2014", "2013", "2012", "2011", "2010", "2009"]}, {"Modelo": "CB 450 DX", "Anos": ["1994", "1993", "1992", "1991", "1990"]}, {"Modelo": "CB 500", "Anos": ["2005", "2004", "2003", "2002", "2001", "2000", "1999", "1998", "1997"]}, {"Modelo": "CB 500F", "Anos": ["32000", "2022", "2021", "2020", "2019", "2018", "2017", "2016", "2015", "2014"]}, {"Modelo": "CB 500X", "Anos": ["32000", "2022", "2021", "2020", "2019", "2018", "2017", "2016", "2015", "2014", "2013"]}, {"Modelo": "CB 600F HORNET", "Anos": ["2015", "2014", "2013", "2012", "2011", "2010", "2009", "2008", "2007", "2006", "2005"]}, {"Modelo": "CB 650F", "Anos": ["32000", "2019", "2018", "2017", "2016", "2015"]}, {"Modelo": "CB 650R", "Anos": ["32000", "2021", "2020"]}, {"Modelo": "CB TWISTER/FLEXONE 250cc", "Anos": ["32000", "2021", "2020", "2019", "2018", "2017", "2016"]}, {"Modelo": "CB1300 SUPER FOUR", "Anos": ["2008", "2007"]}, {"Modelo": "CBR 1000 F", "Anos": ["1996", "1995", "1994", "1993", "1992", "1991"]}, {"Modelo": "CBR 1000 RR Fireblade", "Anos": ["32000", "2020", "2019", "2018", "2015", "2014", "2013", "2012", "2011", "2010", "2009", "2008", "2007", "2006", "2005", "2004"]}, {"Modelo": "CBR 1000 RR Fireblade SP", "Anos": ["32000", "2020", "2019", "2018", "2017"]}, {"Modelo": "CBR 1000 RR-R Fireblade SP", "Anos": ["32000", "2022"]}, {"Modelo": "CBR 1100 XX SUPER BLACKBIRD", "Anos": ["2006", "2005", "2004", "2003", "2002", "2001", "2000", "1999", "1998", "1997"]}, {"Modelo": "CBR 250R", "Anos": ["2012"]}, {"Modelo": "CBR 450", "Anos": ["1995", "1994", "1993", "1992", "1991", "1990"]}, {"Modelo": "CBR 450 SR", "Anos": ["1995", "1994", "1993", "1992", "1991", "1990"]}, {"Modelo": "CBR 500R", "Anos": ["2018", "2017", "2016", "2015", "2014"]}, {"Modelo": "CBR 600 F", "Anos": ["2015", "2014", "2013", "2012", "2002", "2001", "2000", "1999", "1998", "1997", "1996", "1995", "1994", "1993", "1992"]}, {"Modelo": "CBR 600 RR", "Anos": ["2014", "2013", "2012", "2011", "2010", "2009", "2008", "2007", "2006", "2005", "2004", "2003"]}, {"Modelo": "CBR 650 R", "Anos": ["32000", "2021", "2020"]}, {"Modelo": "CBR 650F", "Anos": ["2019", "2018", "2017", "2016", "2015"]}, {"Modelo": "CBR 900 RR FIRE BLADE", "Anos": ["2004", "2003", "2002", "2001", "2000", "1999", "1998", "1997", "1996", "1995", "1994", "1993"]}, {"Modelo": "CBX 150 AERO", "Anos": ["1993", "1992", "1991", "1990"]}, {"Modelo": "CBX 200 STRADA", "Anos": ["2003", "2002", "2001", "2000", "1999", "1998", "1997", "1996", "1995", "1994", "1993"]}, {"Modelo": "CBX 250 TWISTER", "Anos": ["2008", "2007", "2006", "2005", "2004", "2003", "2002", "2001"]}, {"Modelo": "CBX 750 FOUR", "Anos": ["1990"]}, {"Modelo": "CBX 750 FOUR INDY", "Anos": ["1995", "1994", "1993", "1992", "1991", "1990"]}, {"Modelo": "CBX 750 R", "Anos": ["1990"]}, {"Modelo": "CG 125", "Anos": ["1990"]}, {"Modelo": "CG 125 CARGO ES", "Anos": ["2013", "2012", "2011", "2010", "2009"]}, {"Modelo": "CG 125 CARGO ESD", "Anos": ["2015", "2014"]}, {"Modelo": "CG 125 CARGO/ CARGO KS/125i CARGO", "Anos": ["2018", "2017", "2016", "2015", "2014", "2013", "2012", "2011", "2010", "2009", "2004", "2003", "2002", "2001", "2000", "1999", "1998", "1997", "1996", "1995", "1994", "1993", "1992", "1991", "1990"]}, {"Modelo": "CG 125 FAN / FAN KS / 125 i FAN", "Anos": ["2018", "2017", "2016", "2015", "2014", "2013", "2012", "2011", "2010", "2009", "2008", "2007", "2006", "2005"]}, {"Modelo": "CG 125 FAN ES", "Anos": ["2015", "2014", "2013", "2012", "2011", "2010", "2009"]}, {"Modelo": "CG 125 FAN ESD", "Anos": ["2015", "2014"]}, {"Modelo": "CG 125 TITAN", "Anos": ["2000", "1999", "1998", "1997", "1996", "1995", "1994"]}, {"Modelo": "CG 125 TITAN-ES", "Anos": ["2004", "2003", "2002", "2001", "2000", "1999"]}, {"Modelo": "CG 125 TITAN-KS", "Anos": ["2004", "2003", "2002", "2001", "2000", "1999"]}, {"Modelo": "CG 125 TITAN-KSE", "Anos": ["2004", "2003", "2002"]}, {"Modelo": "CG 125 TODAY", "Anos": ["1994", "1993", "1992", "1991", "1990"]}, {"Modelo": "CG 150 CARGO ESD FLEX", "Anos": ["2015", "2014", "2013"]}, {"Modelo": "CG 150 FAN ESDi/ 150 FAN ESDi FLEX", "Anos": ["2015", "2014", "2013", "2012", "2011"]}, {"Modelo": "CG 150 FAN ESi/ 150 FAN ESi FLEX", "Anos": ["2013", "2012", "2011", "2010"]}, {"Modelo": "CG 150 SPORT", "Anos": ["2008", "2007", "2006", "2005"]}, {"Modelo": "CG 150 START FLEXONE", "Anos": ["2016", "2015"]}, {"Modelo": "CG 150 TITAN-ES", "Anos": ["2009", "2008", "2007", "2006", "2005", "2004"]}, {"Modelo": "CG 150 TITAN-ES MIX", "Anos": ["2010", "2009"]}, {"Modelo": "CG 150 TITAN-ESD MIX/FLEX", "Anos": ["2015", "2014", "2013", "2012", "2011", "2010", "2009"]}, {"Modelo": "CG 150 TITAN-ESD/ TITAN SPECIAL EDITION", "Anos": ["2009", "2008", "2007", "2006", "2005", "2004"]}, {"Modelo": "CG 150 TITAN-EX MIX/FLEX", "Anos": ["2015", "2014", "2013", "2012", "2011", "2010"]}, {"Modelo": "CG 150 TITAN-KS MIX", "Anos": ["2011", "2010", "2009"]}, {"Modelo": "CG 150 TITAN-KS/ TITAN-JOB", "Anos": ["2009", "2008", "2007", "2006", "2005", "2004"]}, {"Modelo": "CG 160 CARGO", "Anos": ["32000", "2022", "2021", "2020", "2019", "2018", "2017", "2016"]}, {"Modelo": "CG 160 FAN ESDi FLEXONE", "Anos": ["2017", "2016"]}, {"Modelo": "CG 160 FAN Flex", "Anos": ["32000", "2022", "2021", "2020", "2019", "2018"]}, {"Modelo": "CG 160 START", "Anos": ["32000", "2022", "2021", "2020", "2019", "2018", "2017", "2016"]}, {"Modelo": "CG 160 TITAN 25TH ANNIVERSARY", "Anos": ["2019"]}, {"Modelo": "CG 160 TITAN FLEXONE/Ed.Especial 40 Anos", "Anos": ["32000", "2022", "2021", "2020", "2019", "2018", "2017", "2016"]}, {"Modelo": "CG 160 TITAN S Flex", "Anos": ["32000", "2021", "2020"]}, {"Modelo": "CH 125-R SPACY", "Anos": ["1996", "1995", "1994"]}, {"Modelo": "CR 125", "Anos": ["2006", "2004", "2003", "2002", "2001", "2000", "1999", "1998", "1997", "1996", "1995", "1994", "1991"]}, {"Modelo": "CR 250", "Anos": ["2004", "2003", "2002", "2001", "2000", "1999", "1998", "1997", "1996", "1995", "1994", "1993", "1992", "1991"]}, {"Modelo": "CR 80", "Anos": ["2002", "2001", "2000", "1999", "1998", "1997", "1996", "1995", "1994", "1993", "1992"]}, {"Modelo": "CRF 1000L AFRICA TWIN", "Anos": ["32000", "2020", "2018", "2017"]}, {"Modelo": "CRF 1000L AFRICA TWIN ADV. SPORTS TE", "Anos": ["32000", "2020"]}, {"Modelo": "CRF 1000L AFRICA TWIN ADVENTURE SPORTS", "Anos": ["32000", "2020"]}, {"Modelo": "CRF 1000L AFRICA TWIN TE", "Anos": ["32000", "2020", "2018", "2017"]}, {"Modelo": "CRF 1100L AFRICA TWIN", "Anos": ["32000", "2021"]}, {"Modelo": "CRF 1100L AFRICA TWIN ADV. SPORTS ES", "Anos": ["32000", "2021"]}, {"Modelo": "CRF 110F", "Anos": ["2013"]}, {"Modelo": "CRF 150F", "Anos": ["2017", "2016", "2015", "2014", "2013", "2012"]}, {"Modelo": "CRF 230 F", "Anos": ["32000", "2020", "2019", "2018", "2017", "2016", "2015", "2014", "2013", "2012", "2011", "2010", "2009", "2008", "2007"]}, {"Modelo": "CRF 250 F", "Anos": ["32000", "2022", "2021", "2020", "2019"]}, {"Modelo": "CRF 250 X", "Anos": ["2009", "2008", "2007"]}, {"Modelo": "CRF 250L", "Anos": ["2013"]}, {"Modelo": "CRF 450 R", "Anos": ["32000", "2021", "2020", "2019"]}, {"Modelo": "CRF 450 RX", "Anos": ["32000", "2021", "2020", "2019"]}, {"Modelo": "CRF 450 X", "Anos": ["32000", "2021", "2020", "2019"]}, {"Modelo": "CTX 700N", "Anos": ["2014"]}, {"Modelo": "DOMINATOR 650", "Anos": ["1994", "1993", "1992"]}, {"Modelo": "ELITE 125", "Anos": ["32000", "2021", "2020", "2019"]}, {"Modelo": "GOLD WING 1500/ 1800", "Anos": ["32000", "2019", "2015", "2014", "2013", "2012", "2011", "2010", "2009", "2008", "2007", "2006", "2005", "2004", "2003", "2002", "2001", "2000", "1999", "1998", "1997", "1996", "1995", "1994", "1993"]}, {"Modelo": "GOLD WING TOUR 1800", "Anos": ["32000", "2019"]}, {"Modelo": "LEAD 110", "Anos": ["2016", "2015", "2014", "2013", "2012", "2011", "2010"]}, {"Modelo": "MAGNA 750", "Anos": ["1998", "1997", "1996", "1995", "1994"]}, {"Modelo": "NC 700 X/ 700X ABS", "Anos": ["2015", "2014", "2013"]}, {"Modelo": "NC 750X/NC 750X ABS", "Anos": ["32000", "2021", "2020", "2019", "2018", "2017", "2016", "2015"]}, {"Modelo": "NX 150", "Anos": ["1993", "1992", "1991", "1990"]}, {"Modelo": "NX 200", "Anos": ["2001", "2000", "1999", "1998", "1997", "1996", "1995", "1994", "1993"]}, {"Modelo": "NX 350 SAHARA", "Anos": ["1999", "1998", "1997", "1996", "1995", "1994", "1993", "1992", "1991", "1990"]}, {"Modelo": "NX 400i FALCON", "Anos": ["2015", "2014", "2013"]}, {"Modelo": "NX-4 FALCON 400", "Anos": ["2008", "2007", "2006", "2005", "2004", "2003", "2002", "2001", "2000", "1999"]}, {"Modelo": "NXR 125 BROS ES", "Anos": ["2015", "2014", "2013", "2005", "2004", "2003"]}, {"Modelo": "NXR 125 BROS KS", "Anos": ["2014", "2013", "2005", "2004", "2003"]}, {"Modelo": "NXR 150 BROS ES", "Anos": ["2009", "2008", "2007", "2006"]}, {"Modelo": "NXR 150 BROS ES MIX/FLEX", "Anos": ["2014", "2013", "2012", "2011", "2010"]}, {"Modelo": "NXR 150 BROS ESD", "Anos": ["2009", "2008", "2007", "2006", "2005", "2004", "2003"]}, {"Modelo": "NXR 150 BROS ESD MIX/FLEX", "Anos": ["2015", "2014", "2013", "2012", "2011", "2010"]}, {"Modelo": "NXR 150 BROS KS", "Anos": ["2010", "2009", "2008", "2007", "2006"]}, {"Modelo": "NXR 150 BROS KS MIX/FLEX", "Anos": ["2012", "2011", "2010"]}, {"Modelo": "NXR 160 BROS", "Anos": ["2018", "2017", "2016"]}, {"Modelo": "NXR 160 BROS ESD FLEXONE", "Anos": ["2016", "2015"]}, {"Modelo": "NXR 160 BROS ESDD FLEXONE", "Anos": ["32000", "2022", "2021", "2020", "2019", "2018", "2017", "2016", "2015"]}, {"Modelo": "PCX 150 SPORT", "Anos": ["32000", "2022", "2021", "2020", "2019", "2018"]}, {"Modelo": "PCX 150/DLX", "Anos": ["32000", "2022", "2021", "2020", "2019", "2018", "2017", "2016", "2015", "2014", "2013"]}, {"Modelo": "POP 100 97cc", "Anos": ["2015", "2014", "2013", "2012", "2011", "2010", "2009", "2008", "2007"]}, {"Modelo": "POP 110i", "Anos": ["32000", "2021", "2020", "2019", "2018", "2017", "2016"]}, {"Modelo": "SH 150i/DLX", "Anos": ["32000", "2021", "2020", "2019", "2018", "2017"]}, {"Modelo": "SH 300i", "Anos": ["32000", "2021", "2020", "2019", "2018", "2017", "2016"]}, {"Modelo": "SH 300i Sport", "Anos": ["32000", "2021", "2020", "2019"]}, {"Modelo": "SHADOW 1100 AC", "Anos": ["2002", "2001", "1999", "1998", "1997", "1996", "1995", "1994"]}, {"Modelo": "SHADOW 1100 OURO", "Anos": ["2000"]}, {"Modelo": "SHADOW AM 750", "Anos": ["2001", "2000", "1999", "1998", "1997"]}, {"Modelo": "SHADOW VT 1100", "Anos": ["1999", "1998", "1997", "1996", "1995", "1994"]}, {"Modelo": "SUPER HAWK 1000", "Anos": ["1998", "1997"]}, {"Modelo": "TRX 350 FOURTRAX  FM QUADRICICLO", "Anos": ["2007", "2006", "2005", "2004"]}, {"Modelo": "TRX 350 FOURTRAX  TM QUADRICICLO", "Anos": ["2007", "2006", "2005", "2004"]}, {"Modelo": "TRX 420 FOURTRAX   TM 4x2 QUADRICICLO", "Anos": ["2015", "2014", "2013", "2012", "2011", "2010", "2008"]}, {"Modelo": "TRX 420 FOURTRAX  FM 4x4 QUADRICICLO", "Anos": ["32000", "2022", "2021", "2020", "2019", "2018", "2017", "2016", "2015", "2014", "2013", "2012", "2011", "2010", "2008"]}, {"Modelo": "VALKYRIE 1500", "Anos": ["1998", "1997"]}, {"Modelo": "VFR 1200F", "Anos": ["2013", "2012", "2011", "2010"]}, {"Modelo": "VFR 1200X CROSSTOURER", "Anos": ["2013", "2012"]}, {"Modelo": "VT 600 C SHADOW", "Anos": ["2005", "2004", "2003", "2002", "2001", "2000", "1999", "1998", "1997", "1996", "1995"]}, {"Modelo": "VT 750 SHADOW", "Anos": ["2014", "2013", "2012", "2011", "2010", "2009", "2008", "2007", "2006"]}, {"Modelo": "VTX 1800R/ 1800S/ 1800C 1795cc", "Anos": ["2007", "2006", "2005", "2004", "2002"]}, {"Modelo": "X-ADV 745cc", "Anos": ["32000", "2021", "2020", "2019", "2018", "2017"]}, {"Modelo": "XL 1000V VARADERO", "Anos": ["2009", "2008", "2007"]}, {"Modelo": "XL 125 DUTY", "Anos": ["1991", "1990"]}, {"Modelo": "XL 125 S", "Anos": ["1996", "1995", "1994", "1993", "1992"]}, {"Modelo": "XL 700V TRANSALP", "Anos": ["2014", "2013", "2012", "2011"]}, {"Modelo": "XLR 125", "Anos": ["2003", "2002", "2001", "2000", "1999", "1998", "1997", "1996"]}, {"Modelo": "XLR 125 ES", "Anos": ["2003", "2002", "2001", "2000"]}, {"Modelo": "XLX 250 R", "Anos": ["1994", "1993", "1992", "1991", "1990"]}, {"Modelo": "XLX 350 R", "Anos": ["1991", "1990"]}, {"Modelo": "XR 200 R", "Anos": ["2003", "2002", "2001", "2000", "1999", "1998", "1997", "1996", "1995", "1994"]}, {"Modelo": "XR 250 TORNADO", "Anos": ["2008", "2007", "2006", "2005", "2004", "2003", "2002", "2001"]}, {"Modelo": "XR 650", "Anos": ["1998", "1997"]}, {"Modelo": "XRE 190 ADVENTURE FLEX", "Anos": ["32000", "2021", "2020"]}, {"Modelo": "XRE 190/ Flex", "Anos": ["32000", "2021", "2020", "2019", "2018", "2017", "2016"]}, {"Modelo": "XRE 300 ADVENTURE FLEX", "Anos": ["32000", "2022", "2021", "2020", "2019", "2018", "2017"]}, {"Modelo": "XRE 300 RALLY FLEX", "Anos": ["32000", "2022", "2021", "2020", "2019", "2018", "2017", "2016", "2015", "2014"]}, {"Modelo": "XRE 300/ 300 ABS/ FLEX", "Anos": ["32000", "2022", "2021", "2020", "2019", "2018", "2017", "2016", "2015", "2014", "2013", "2012", "2011", "2010"]}]